todonotifier/__init__.py
todonotifier/config.py
todonotifier/connect.py
todonotifier/constants.py
todonotifier/driver.py
todonotifier/models.py
todonotifier/notifier.py
todonotifier/summary_generators.py
todonotifier/todo_notifier.py
todonotifier/utils.py
todonotifier-1.3.2.dist-info/LICENSE
todonotifier-1.3.2.dist-info/METADATA
todonotifier-1.3.2.dist-info/WHEEL
todonotifier-1.3.2.dist-info/RECORD
