Metadata-Version: 2.1
Name: todonotifier
Version: 1.3.2
Summary: Library to setup automatic TODO Notifications in code
Home-page: https://pypi.org/project/todonotifier/
License: MIT
Author: Ashutosh
Author-email: 37182127+ashu-tosh-kumar@users.noreply.github.com
Requires-Python: >=3.9,<4.0
Classifier: License :: OSI Approved :: MIT License
Classifier: Programming Language :: Python :: 3
Classifier: Programming Language :: Python :: 3.9
Classifier: Programming Language :: Python :: 3.10
Classifier: Programming Language :: Python :: 3.11
Classifier: Programming Language :: Python :: 3.12
Requires-Dist: gitpython (==3.1.42)
Requires-Dist: python-dateutil (==2.8.2)
Project-URL: Documentation, https://ashu-tosh-kumar.github.io/todo_notifier/
Project-URL: Repository, https://github.com/ashu-tosh-kumar/todo_notifier
